[
  {
    "id": "BS08-013",
    "nameEn": "Andrealphas",
    "type": "Spirit",
    "color": "Purple",
    "cost": 3,
    "family": "Nightling",
    "rarity": "Common",
    "set": "BS08",
    "imageUrl": "https://static.wikia.nocookie.net/battle-spirits/images/4/48/BS08-013.jpg/revision/latest?cb=20240218081057",
    "effectRaw": null
  },
  {
    "id": "BS08-044",
    "nameEn": "ArcanaQueen-Pallas",
    "type": "Spirit",
    "color": "Yellow",
    "cost": 5,
    "family": "Magician",
    "rarity": "Uncommon",
    "set": "BS08",
    "imageUrl": "https://static.wikia.nocookie.net/battle-spirits/images/9/9d/BS08-044.jpg/revision/latest?cb=20231007073226",
    "effectRaw": null
  },
  {
    "id": "BS08-021",
    "nameEn": "BlackAmenborg",
    "type": "Spirit",
    "color": "Green",
    "cost": 3,
    "family": "Parasite",
    "rarity": "Common",
    "set": "BS08",
    "imageUrl": "https://static.wikia.nocookie.net/battle-spirits/images/0/04/BS08-021.jpg/revision/latest?cb=20231021154012",
    "effectRaw": null
  },
  {
    "id": "BS08-083",
    "nameEn": "Break Burst",
    "type": "Magic",
    "color": "Blue",
    "cost": 3,
    "family": null,
    "rarity": "Common",
    "set": "BS08",
    "imageUrl": "https://static.wikia.nocookie.net/battle-spirits/images/e/e3/BS08-083.jpg/revision/latest?cb=20230927161554",
    "effectRaw": null
  },
  {
    "id": "BS08-010",
    "nameEn": "Demo-Bone",
    "type": "Spirit",
    "color": "Purple",
    "cost": 1,
    "family": "Zombie",
    "rarity": "Common",
    "set": "BS08",
    "imageUrl": "https://static.wikia.nocookie.net/battle-spirits/images/d/d0/BS08-010.jpg/revision/latest?cb=20260224160603",
    "effectRaw": null
  },
  {
    "id": "BS08-020",
    "nameEn": "Dio-Mantis",
    "type": "Spirit",
    "color": "Green",
    "cost": 2,
    "family": "Parasite",
    "rarity": "Common",
    "set": "BS08",
    "imageUrl": "https://static.wikia.nocookie.net/battle-spirits/images/9/96/BS08-020.jpg/revision/latest?cb=20231021154735",
    "effectRaw": null
  },
  {
    "id": "BS08-067",
    "nameEn": "Dragon Scramble",
    "type": "Magic",
    "color": "Red",
    "cost": 3,
    "family": null,
    "rarity": "Common",
    "set": "BS08",
    "imageUrl": "https://static.wikia.nocookie.net/battle-spirits/images/3/33/BS08-067.jpg/revision/latest?cb=20240729172736",
    "effectRaw": null
  },
  {
    "id": "BS08-069",
    "nameEn": "Judgment Flare",
    "type": "Magic",
    "color": "Red",
    "cost": 6,
    "family": null,
    "rarity": "Common",
    "set": "BS08",
    "imageUrl": "https://static.wikia.nocookie.net/battle-spirits/images/2/27/BS08-069.jpg/revision/latest?cb=20240729131208",
    "effectRaw": null
  },
  {
    "id": "BS08-068",
    "nameEn": "Meteor Storm",
    "type": "Magic",
    "color": "Red",
    "cost": 4,
    "family": null,
    "rarity": "Rare",
    "set": "BS08",
    "imageUrl": "https://static.wikia.nocookie.net/battle-spirits/images/f/fe/BS08-068.jpg/revision/latest?cb=20230816105909",
    "effectRaw": null
  },
  {
    "id": "BS08-072",
    "nameEn": "Mind Break",
    "type": "Magic",
    "color": "Purple",
    "cost": 5,
    "family": null,
    "rarity": "Rare",
    "set": "BS08",
    "imageUrl": "https://static.wikia.nocookie.net/battle-spirits/images/c/ca/BS08-072.jpg/revision/latest?cb=20240729173318",
    "effectRaw": null
  },
  {
    "id": "BS08-081",
    "nameEn": "Royal Straight Flush",
    "type": "Magic",
    "color": "Yellow",
    "cost": 10,
    "family": null,
    "rarity": "Uncommon",
    "set": "BS08",
    "imageUrl": "https://static.wikia.nocookie.net/battle-spirits/images/e/e0/BS08-081.jpg/revision/latest?cb=20231007072116",
    "effectRaw": null
  },
  {
    "id": "BS08-023",
    "nameEn": "The AirCommodore Geran",
    "type": "Spirit",
    "color": "Green",
    "cost": 4,
    "family": "Winged Beast",
    "rarity": "Rare",
    "set": "BS08",
    "imageUrl": "https://static.wikia.nocookie.net/battle-spirits/images/5/5e/BS08-023.jpg/revision/latest?cb=20240616160920",
    "effectRaw": null
  },
  {
    "id": "BS08-040",
    "nameEn": "The Angelia Olifia",
    "type": "Spirit",
    "color": "Yellow",
    "cost": 3,
    "family": "Divine Spirit",
    "rarity": "Common",
    "set": "BS08",
    "imageUrl": "https://static.wikia.nocookie.net/battle-spirits/images/d/da/BS08-040.jpg/revision/latest?cb=20230628195112",
    "effectRaw": null
  },
  {
    "id": "BS08-042",
    "nameEn": "The Angelia Salaty",
    "type": "Spirit",
    "color": "Yellow",
    "cost": 4,
    "family": "Divine Spirit",
    "rarity": "Uncommon",
    "set": "BS08",
    "imageUrl": "https://static.wikia.nocookie.net/battle-spirits/images/9/90/BS08-042.jpg/revision/latest?cb=20231014081243",
    "effectRaw": null
  },
  {
    "id": "BS08-030",
    "nameEn": "The Artifact Fjalar",
    "type": "Spirit",
    "color": "White",
    "cost": 3,
    "family": "Armed Machine",
    "rarity": "Common",
    "set": "BS08",
    "imageUrl": "https://static.wikia.nocookie.net/battle-spirits/images/6/6f/BS08-030.jpg/revision/latest?cb=20230321084235",
    "effectRaw": null
  },
  {
    "id": "BS08-035",
    "nameEn": "The ArtifactBeast Sai-Drigan",
    "type": "Spirit",
    "color": "White",
    "cost": 6,
    "family": "Machine Beast",
    "rarity": "Master Rare",
    "set": "BS08",
    "imageUrl": "https://static.wikia.nocookie.net/battle-spirits/images/4/45/BS08-035.jpg/revision/latest?cb=20230711135003",
    "effectRaw": null
  },
  {
    "id": "BS08-008",
    "nameEn": "The BlackEmperorDragon Darkwurm",
    "type": "Spirit",
    "color": "Red",
    "cost": 6,
    "family": "Astral Dragon",
    "rarity": "Rare",
    "set": "BS08",
    "imageUrl": "https://static.wikia.nocookie.net/battle-spirits/images/0/01/BS08-008.jpg/revision/latest?cb=20230107110628",
    "effectRaw": null
  },
  {
    "id": "BS08-005",
    "nameEn": "The BraveGeneral Catapuldos",
    "type": "Spirit",
    "color": "Red",
    "cost": 4,
    "family": "Ancient Dragon",
    "rarity": "Common",
    "set": "BS08",
    "imageUrl": "https://static.wikia.nocookie.net/battle-spirits/images/7/74/BS08-005.jpg/revision/latest?cb=20251005165419",
    "effectRaw": null
  },
  {
    "id": "BS08-045",
    "nameEn": "The Braver Phoenixpentan",
    "type": "Spirit",
    "color": "Yellow",
    "cost": 7,
    "family": "Song Bird",
    "rarity": "Master Rare",
    "set": "BS08",
    "imageUrl": "https://static.wikia.nocookie.net/battle-spirits/images/9/9c/BS08-045.jpg/revision/latest?cb=20231021163802",
    "effectRaw": null
  },
  {
    "id": "BS08-038",
    "nameEn": "The CatGirl Annie",
    "type": "Spirit",
    "color": "Yellow",
    "cost": 2,
    "family": "Imaginary Beast",
    "rarity": "Common",
    "set": "BS08",
    "imageUrl": "https://static.wikia.nocookie.net/battle-spirits/images/5/55/BS08-038.jpg/revision/latest?cb=20240209181045",
    "effectRaw": null
  },
  {
    "id": "BS08-054",
    "nameEn": "The ChimeraSacredBeast Cthulhum",
    "type": "Spirit",
    "color": "Blue",
    "cost": 7,
    "family": "Fusion Beast",
    "rarity": "Master Rare",
    "set": "BS08",
    "imageUrl": "https://static.wikia.nocookie.net/battle-spirits/images/1/15/BS08-054.jpg/revision/latest?cb=20231021164442",
    "effectRaw": null
  },
  {
    "id": "BS08-015",
    "nameEn": "The DarkDragonRider Sabna-Rook",
    "type": "Spirit",
    "color": "Purple",
    "cost": 5,
    "family": "Dragon Knight",
    "rarity": "Uncommon",
    "set": "BS08",
    "imageUrl": "https://static.wikia.nocookie.net/battle-spirits/images/d/d6/BS08-015.jpg/revision/latest?cb=20231007084534",
    "effectRaw": null
  },
  {
    "id": "BS08-012",
    "nameEn": "The DarkSkulldemon",
    "type": "Spirit",
    "color": "Purple",
    "cost": 3,
    "family": "Infernal Lord",
    "rarity": "Common",
    "set": "BS08",
    "imageUrl": "https://static.wikia.nocookie.net/battle-spirits/images/7/78/BS08-012.jpg/revision/latest?cb=20240218083203",
    "effectRaw": null
  },
  {
    "id": "BS08-004",
    "nameEn": "The Dinoman Tyrannoid",
    "type": "Spirit",
    "color": "Red",
    "cost": 3,
    "family": "Dragon",
    "rarity": "Uncommon",
    "set": "BS08",
    "imageUrl": "https://static.wikia.nocookie.net/battle-spirits/images/a/af/BS08-004.jpg/revision/latest?cb=20230701163709",
    "effectRaw": null
  },
  {
    "id": "BS08-041",
    "nameEn": "The DogGeneral Cu-Sith",
    "type": "Spirit",
    "color": "Yellow",
    "cost": 4,
    "family": "Imaginary Beast",
    "rarity": "Common",
    "set": "BS08",
    "imageUrl": "https://static.wikia.nocookie.net/battle-spirits/images/7/76/BS08-041.jpg/revision/latest?cb=20240807164907",
    "effectRaw": null
  },
  {
    "id": "BS08-009",
    "nameEn": "The FieldMarshalEmperor Dragron",
    "type": "Spirit",
    "color": "Red",
    "cost": 7,
    "family": "Dragon",
    "rarity": "Master Rare",
    "set": "BS08",
    "imageUrl": "https://static.wikia.nocookie.net/battle-spirits/images/a/a7/BS08-009.jpg/revision/latest?cb=20231021171456",
    "effectRaw": null
  },
  {
    "id": "BS08-X34",
    "nameEn": "The GodMadeSoldier Orichalcum-Golem",
    "type": "Spirit",
    "color": "Blue",
    "cost": 7,
    "family": "Artificial Soldier",
    "rarity": "X-Rare",
    "set": "BS08",
    "imageUrl": "https://static.wikia.nocookie.net/battle-spirits/images/6/65/BS08-X34.jpg/revision/latest?cb=20230714060554",
    "effectRaw": null
  },
  {
    "id": "BS08-062",
    "nameEn": "The Gravity Dimension Engine",
    "type": "Nexus",
    "color": "White",
    "cost": 3,
    "family": null,
    "rarity": "Common",
    "set": "BS08",
    "imageUrl": "https://static.wikia.nocookie.net/battle-spirits/images/4/4f/BS08-062.jpg/revision/latest?cb=20240810034649",
    "effectRaw": null
  },
  {
    "id": "BS08-X31",
    "nameEn": "The GreatKing Blacktaurus",
    "type": "Spirit",
    "color": "Green",
    "cost": 8,
    "family": "Shell Insect",
    "rarity": "X-Rare",
    "set": "BS08",
    "imageUrl": "https://static.wikia.nocookie.net/battle-spirits/images/c/cb/BS08-X31.jpg/revision/latest?cb=20230627153447",
    "effectRaw": null
  },
  {
    "id": "BS08-024",
    "nameEn": "The GroundDragonRider Vespeniar",
    "type": "Spirit",
    "color": "Green",
    "cost": 5,
    "family": "Dragon Knight",
    "rarity": "Uncommon",
    "set": "BS08",
    "imageUrl": "https://static.wikia.nocookie.net/battle-spirits/images/e/e7/BS08-024.jpg/revision/latest?cb=20231007085052",
    "effectRaw": null
  },
  {
    "id": "BS08-033",
    "nameEn": "The GuardianBeast Snopard",
    "type": "Spirit",
    "color": "White",
    "cost": 4,
    "family": "Machine Beast",
    "rarity": "Uncommon",
    "set": "BS08",
    "imageUrl": "https://static.wikia.nocookie.net/battle-spirits/images/3/3c/BS08-033.jpg/revision/latest?cb=20230517061204",
    "effectRaw": null
  },
  {
    "id": "BS08-026",
    "nameEn": "The HeavyArmoredBug Goliearth",
    "type": "Spirit",
    "color": "Green",
    "cost": 6,
    "family": "Shell Insect",
    "rarity": "Uncommon",
    "set": "BS08",
    "imageUrl": "https://static.wikia.nocookie.net/battle-spirits/images/e/ef/BS08-026.jpg/revision/latest?cb=20240110060004",
    "effectRaw": null
  },
  {
    "id": "BS08-014",
    "nameEn": "The HellGeneral Amaimon",
    "type": "Spirit",
    "color": "Purple",
    "cost": 4,
    "family": "Infernal Lord",
    "rarity": "Common",
    "set": "BS08",
    "imageUrl": "https://static.wikia.nocookie.net/battle-spirits/images/d/da/BS08-014.jpg/revision/latest?cb=20230709135054",
    "effectRaw": null
  },
  {
    "id": "BS08-031",
    "nameEn": "The HellSacred Gungnir",
    "type": "Spirit",
    "color": "White",
    "cost": 3,
    "family": "Armed Machine",
    "rarity": "Common",
    "set": "BS08",
    "imageUrl": "https://static.wikia.nocookie.net/battle-spirits/images/b/b5/BS08-031.jpg/revision/latest?cb=20230711084651",
    "effectRaw": null
  },
  {
    "id": "BS08-016",
    "nameEn": "The HellSerpentineMan Botis",
    "type": "Spirit",
    "color": "Purple",
    "cost": 5,
    "family": "Infernal Lord",
    "rarity": "Rare",
    "set": "BS08",
    "imageUrl": "https://static.wikia.nocookie.net/battle-spirits/images/8/8d/BS08-016.jpg/revision/latest?cb=20231110150225",
    "effectRaw": null
  },
  {
    "id": "BS08-011",
    "nameEn": "The HellWolf Armon",
    "type": "Spirit",
    "color": "Purple",
    "cost": 2,
    "family": "Infernal Lord",
    "rarity": "Common",
    "set": "BS08",
    "imageUrl": "https://static.wikia.nocookie.net/battle-spirits/images/6/61/BS08-011.jpg/revision/latest?cb=20240218075232",
    "effectRaw": null
  },
  {
    "id": "BS08-055",
    "nameEn": "The ImperialDragoon's Round Table",
    "type": "Nexus",
    "color": "Red",
    "cost": 3,
    "family": null,
    "rarity": "Uncommon",
    "set": "BS08",
    "imageUrl": "https://static.wikia.nocookie.net/battle-spirits/images/c/c4/BS08-055.jpg/revision/latest?cb=20240207132557",
    "effectRaw": null
  },
  {
    "id": "BS08-043",
    "nameEn": "The LightDragonRider Arcanajoker",
    "type": "Spirit",
    "color": "Yellow",
    "cost": 5,
    "family": "Dragon Knight",
    "rarity": "Rare",
    "set": "BS08",
    "imageUrl": "https://static.wikia.nocookie.net/battle-spirits/images/f/ff/BS08-043.jpg/revision/latest?cb=20231007082921",
    "effectRaw": null
  },
  {
    "id": "BS08-036",
    "nameEn": "The MachineDeity Inphenit-Wols",
    "type": "Spirit",
    "color": "White",
    "cost": 10,
    "family": "Vanity Deity",
    "rarity": "Master Rare",
    "set": "BS08",
    "imageUrl": "https://static.wikia.nocookie.net/battle-spirits/images/8/84/BS08-036.jpg/revision/latest?cb=20230613050104",
    "effectRaw": null
  },
  {
    "id": "BS08-X29",
    "nameEn": "The MasterDragonRider Dark-Crimson",
    "type": "Spirit",
    "color": "Red",
    "cost": 7,
    "family": "Dragon Knight",
    "rarity": "X-Rare",
    "set": "BS08",
    "imageUrl": "https://static.wikia.nocookie.net/battle-spirits/images/1/1a/BS08-X29.jpg/revision/latest?cb=20230816101744",
    "effectRaw": null
  },
  {
    "id": "BS08-029",
    "nameEn": "The Narwhal Monokerock",
    "type": "Spirit",
    "color": "White",
    "cost": 3,
    "family": "Flying Fish",
    "rarity": "Uncommon",
    "set": "BS08",
    "imageUrl": "https://static.wikia.nocookie.net/battle-spirits/images/2/23/BS08-029.jpg/revision/latest?cb=20231020161157",
    "effectRaw": null
  },
  {
    "id": "BS08-064",
    "nameEn": "The PhoenixCalibur",
    "type": "Nexus",
    "color": "Yellow",
    "cost": 3,
    "family": null,
    "rarity": "Common",
    "set": "BS08",
    "imageUrl": "https://static.wikia.nocookie.net/battle-spirits/images/6/66/BS08-064.jpg/revision/latest?cb=20251026123902",
    "effectRaw": null
  },
  {
    "id": "BS08-007",
    "nameEn": "The PyroclasticDragon Prometeors",
    "type": "Spirit",
    "color": "Red",
    "cost": 5,
    "family": "Astral Dragon",
    "rarity": "Uncommon",
    "set": "BS08",
    "imageUrl": "https://static.wikia.nocookie.net/battle-spirits/images/9/9f/BS08-007.jpg/revision/latest?cb=20240729140614",
    "effectRaw": null
  },
  {
    "id": "BS08-025",
    "nameEn": "The Queen Antreine",
    "type": "Spirit",
    "color": "Green",
    "cost": 5,
    "family": "Parasite",
    "rarity": "Rare",
    "set": "BS08",
    "imageUrl": "https://static.wikia.nocookie.net/battle-spirits/images/e/e1/BS08-025.jpg/revision/latest?cb=20230627150821",
    "effectRaw": null
  },
  {
    "id": "BS08-057",
    "nameEn": "The Red Sand Glass",
    "type": "Nexus",
    "color": "Purple",
    "cost": 3,
    "family": null,
    "rarity": "Common",
    "set": "BS08",
    "imageUrl": "https://static.wikia.nocookie.net/battle-spirits/images/1/18/BS08-057.jpg/revision/latest?cb=20240606085415",
    "effectRaw": null
  },
  {
    "id": "BS08-061",
    "nameEn": "The Resonant Tuning Fork Tower",
    "type": "Nexus",
    "color": "White",
    "cost": 3,
    "family": null,
    "rarity": "Rare",
    "set": "BS08",
    "imageUrl": "https://static.wikia.nocookie.net/battle-spirits/images/f/f9/BS08-061.jpg/revision/latest?cb=20231103200748",
    "effectRaw": null
  },
  {
    "id": "BS08-032",
    "nameEn": "The ResourcefulGeneral Gondlir",
    "type": "Spirit",
    "color": "White",
    "cost": 4,
    "family": "Android",
    "rarity": "Common",
    "set": "BS08",
    "imageUrl": "https://static.wikia.nocookie.net/battle-spirits/images/1/13/BS08-032.jpg/revision/latest?cb=20231112084307",
    "effectRaw": null
  },
  {
    "id": "BS08-053",
    "nameEn": "The ReverieBonze Sanzorl",
    "type": "Spirit",
    "color": "Blue",
    "cost": 5,
    "family": "Beast Head",
    "rarity": "Rare",
    "set": "BS08",
    "imageUrl": "https://static.wikia.nocookie.net/battle-spirits/images/f/ff/BS08-053.jpg/revision/latest?cb=20231021180033",
    "effectRaw": null
  },
  {
    "id": "BS08-066",
    "nameEn": "The Ruins of the Seabed",
    "type": "Nexus",
    "color": "Blue",
    "cost": 4,
    "family": null,
    "rarity": "Rare",
    "set": "BS08",
    "imageUrl": "https://static.wikia.nocookie.net/battle-spirits/images/5/54/BS08-066.jpg/revision/latest?cb=20230509065939",
    "effectRaw": null
  },
  {
    "id": "BS08-052",
    "nameEn": "The SeaDragonRider Vang-Tholomew",
    "type": "Spirit",
    "color": "Blue",
    "cost": 5,
    "family": "Dragon Knight",
    "rarity": "Uncommon",
    "set": "BS08",
    "imageUrl": "https://static.wikia.nocookie.net/battle-spirits/images/4/48/BS08-052.jpg/revision/latest?cb=20230204160824",
    "effectRaw": null
  },
  {
    "id": "BS08-X30",
    "nameEn": "The SevenShogun Asmodios",
    "type": "Spirit",
    "color": "Purple",
    "cost": 9,
    "family": "Infernal Lord",
    "rarity": "X-Rare",
    "set": "BS08",
    "imageUrl": "https://static.wikia.nocookie.net/battle-spirits/images/3/35/BS08-X30.jpg/revision/latest?cb=20230714075929",
    "effectRaw": null
  },
  {
    "id": "BS08-027",
    "nameEn": "The ShiningWings JewelgΣ",
    "type": "Spirit",
    "color": "Green",
    "cost": 7,
    "family": "Shellman",
    "rarity": "Master Rare",
    "set": "BS08",
    "imageUrl": "https://static.wikia.nocookie.net/battle-spirits/images/b/b2/BS08-027.jpg/revision/latest?cb=20231021162950",
    "effectRaw": null
  },
  {
    "id": "BS08-017",
    "nameEn": "The SkeletonSnake Skullpione",
    "type": "Spirit",
    "color": "Purple",
    "cost": 6,
    "family": "Zombie",
    "rarity": "Master Rare",
    "set": "BS08",
    "imageUrl": "https://static.wikia.nocookie.net/battle-spirits/images/2/2f/BS08-017.jpg/revision/latest?cb=20230709165909",
    "effectRaw": null
  },
  {
    "id": "BS08-034",
    "nameEn": "The SkyDragonRider Platinam",
    "type": "Spirit",
    "color": "White",
    "cost": 5,
    "family": "Dragon Knight",
    "rarity": "Rare",
    "set": "BS08",
    "imageUrl": "https://static.wikia.nocookie.net/battle-spirits/images/5/5d/BS08-034.jpg/revision/latest?cb=20231007085840",
    "effectRaw": null
  },
  {
    "id": "BS08-056",
    "nameEn": "The Sunstone Shrine",
    "type": "Nexus",
    "color": "Red",
    "cost": 5,
    "family": null,
    "rarity": "Common",
    "set": "BS08",
    "imageUrl": "https://static.wikia.nocookie.net/battle-spirits/images/7/71/BS08-056.jpg/revision/latest?cb=20240606082338",
    "effectRaw": null
  },
  {
    "id": "BS08-018",
    "nameEn": "The SupremeDarkKnight Schwart",
    "type": "Spirit",
    "color": "Purple",
    "cost": 7,
    "family": "Evil Shadow",
    "rarity": "Master Rare",
    "set": "BS08",
    "imageUrl": "https://static.wikia.nocookie.net/battle-spirits/images/b/b4/BS08-018.jpg/revision/latest?cb=20231021165036",
    "effectRaw": null
  },
  {
    "id": "BS08-006",
    "nameEn": "The ThunderDragonRider Rayblitz",
    "type": "Spirit",
    "color": "Red",
    "cost": 5,
    "family": "Dragon Knight",
    "rarity": "Rare",
    "set": "BS08",
    "imageUrl": "https://static.wikia.nocookie.net/battle-spirits/images/c/c0/BS08-006.jpg/revision/latest?cb=20231007084004",
    "effectRaw": null
  },
  {
    "id": "X003A",
    "nameEn": "The UltimateDragonRider Sieg-Crimson",
    "type": "Spirit",
    "color": "Red",
    "cost": 6,
    "family": "Dragon Knight",
    "rarity": "X-Rare",
    "set": "Promo",
    "imageUrl": "https://static.wikia.nocookie.net/battle-spirits/images/e/e5/X003A.jpg/revision/latest?cb=20231014093402",
    "effectRaw": null
  },
  {
    "id": "BS08-051",
    "nameEn": "The VeteranGeneral Dogu-Golem",
    "type": "Spirit",
    "color": "Blue",
    "cost": 4,
    "family": "Artificial Soldier",
    "rarity": "Common",
    "set": "BS08",
    "imageUrl": "https://static.wikia.nocookie.net/battle-spirits/images/e/e7/BS08-051.jpg/revision/latest?cb=20251005171400",
    "effectRaw": null
  },
  {
    "id": "BS08-X32",
    "nameEn": "The WingDeity Grand-Woden",
    "type": "Spirit",
    "color": "White",
    "cost": 8,
    "family": "Armed Machine",
    "rarity": "X-Rare",
    "set": "BS08",
    "imageUrl": "https://static.wikia.nocookie.net/battle-spirits/images/8/8b/BS08-X32.jpg/revision/latest?cb=20230430172143",
    "effectRaw": null
  },
  {
    "id": "BS08-063",
    "nameEn": "The Winner's Green Field",
    "type": "Nexus",
    "color": "Yellow",
    "cost": 3,
    "family": null,
    "rarity": "Common",
    "set": "BS08",
    "imageUrl": "https://static.wikia.nocookie.net/battle-spirits/images/4/46/BS08-063.jpg/revision/latest?cb=20240810040152",
    "effectRaw": null
  },
  {
    "id": "BS11-026",
    "nameEn": "Thousandneedle",
    "type": "Spirit",
    "color": "White",
    "cost": 2,
    "family": "Flying Fish",
    "rarity": "Common",
    "set": "BS08",
    "imageUrl": "https://static.wikia.nocookie.net/battle-spirits/images/8/89/BS11-026.jpg/revision/latest?cb=20231112082755",
    "effectRaw": null
  }
]